haiqvML/__init__.py
haiqvML/client.py
haiqvML/track.py
HaiqvML-0.0.1.dist-info/METADATA
HaiqvML-0.0.1.dist-info/WHEEL
HaiqvML-0.0.1.dist-info/top_level.txt
HaiqvML-0.0.1.dist-info/RECORD
